git_credential_helpers/__init__.py
git_credential_helpers/github_app.py
git_credential_helpers-0.2.dist-info/LICENSE
git_credential_helpers-0.2.dist-info/METADATA
git_credential_helpers-0.2.dist-info/WHEEL
git_credential_helpers-0.2.dist-info/entry_points.txt
git_credential_helpers-0.2.dist-info/top_level.txt
git_credential_helpers-0.2.dist-info/RECORD
