Metadata-Version: 2.1
Name: git-credential-helpers
Version: 0.2
Summary: Collection of git-credential helpers
Home-page: https://github.com/yuvipanda/git-credential-helpers
Author: Yuvi Panda
Author-email: yuvipanda@gmail.com
License: 3-clause BSD
Platform: any
Requires-Dist: github3.py
